jupyterlab_mutableai/__init__.py
jupyterlab_mutableai/_version.py
jupyterlab_mutableai/autocomplete_view.py
jupyterlab_mutableai/check_status_view.py
jupyterlab_mutableai/command_line.py
jupyterlab_mutableai/file_action_view.py
jupyterlab_mutableai/handlers.py
jupyterlab_mutableai/transform_view.py
jupyterlab_mutableai/utils.py
jupyterlab_mutableai/labextension/build_log.json
jupyterlab_mutableai/labextension/package.json
jupyterlab_mutableai/labextension/schemas/jupyterlab_mutableai/IMutableAI.json
jupyterlab_mutableai/labextension/schemas/jupyterlab_mutableai/completer.json
jupyterlab_mutableai/labextension/schemas/jupyterlab_mutableai/package.json.orig
jupyterlab_mutableai/labextension/static/lib_index_js.4ab81b7f24dcf8839aeb.js
jupyterlab_mutableai/labextension/static/lib_index_js.4ab81b7f24dcf8839aeb.js.map
jupyterlab_mutableai/labextension/static/remoteEntry.97e441e6c2d86bcf1286.js
jupyterlab_mutableai/labextension/static/remoteEntry.97e441e6c2d86bcf1286.js.map
jupyterlab_mutableai/labextension/static/style.js
jupyterlab_mutableai/labextension/static/style_index_js.5af6e38d55641dddfc0b.js
jupyterlab_mutableai/labextension/static/style_index_js.5af6e38d55641dddfc0b.js.map
jupyterlab_mutableai/labextension/static/vendors-node_modules_css-loader_dist_runtime_api_js-node_modules_css-loader_dist_runtime_cssW-72eba1.6d3650fbbd0922306cd2.js
jupyterlab_mutableai/labextension/static/vendors-node_modules_css-loader_dist_runtime_api_js-node_modules_css-loader_dist_runtime_cssW-72eba1.6d3650fbbd0922306cd2.js.map
jupyterlab_mutableai/labextension/static/vendors-node_modules_jupyterlab_markedparser-extension_lib_index_js.10b7c57cb61d90208449.js
jupyterlab_mutableai/labextension/static/vendors-node_modules_jupyterlab_markedparser-extension_lib_index_js.10b7c57cb61d90208449.js.map
jupyterlab_mutableai/labextension/static/vendors-node_modules_jupyterlab_toastify_lib_index_js.11261ee6945107d0b6da.js
jupyterlab_mutableai-0.1.21.dist-info/LICENSE
jupyterlab_mutableai-0.1.21.dist-info/METADATA
jupyterlab_mutableai-0.1.21.dist-info/WHEEL
jupyterlab_mutableai-0.1.21.dist-info/entry_points.txt
jupyterlab_mutableai-0.1.21.dist-info/top_level.txt
jupyterlab_mutableai-0.1.21.dist-info/RECORD
